pyretroprint/__init__.py
pyretroprint/atari.py
pyretroprint/epsonfx.py
pyretroprint/page.py
pyretroprint/presenter.py
pyretroprint/pyretroprint.py
pyretroprint-0.1.10.dist-info/LICENSE.txt
pyretroprint-0.1.10.dist-info/METADATA
pyretroprint-0.1.10.dist-info/WHEEL
pyretroprint-0.1.10.dist-info/entry_points.txt
pyretroprint-0.1.10.dist-info/top_level.txt
pyretroprint-0.1.10.dist-info/RECORD
