Metadata-Version: 2.1
Name: pyretroprint
Version: 0.1.10
Summary: PyRetroPrint: Dot-Matrix Emulation for our Bleak Dystopian Future!
Home-page: https://github.com/rubeon/pyretroprint
Author: rubeon
License: UNKNOWN
Project-URL: Bug Reports, https://github.com/rubeon/pyretroprint/issues
Project-URL: Source, https://github.com/rubeon/pyretroprint/
Keywords: retro,glue,atari,emulation
Platform: UNKNOWN
Classifier: Development Status :: 3 - Alpha
Classifier: Intended Audience :: Developers
Classifier: License :: OSI Approved :: MIT License
Classifier: Programming Language :: Python :: 3
Requires-Python: >=3.6, <4
License-File: LICENSE.txt
Requires-Dist: pycairo
